pdfextractdata/__init__.py
pdfextractdata/extract.py
pdfextractdata/preprocessing.py
pdfextractdata-4.9.dist-info/LICENSE
pdfextractdata-4.9.dist-info/METADATA
pdfextractdata-4.9.dist-info/WHEEL
pdfextractdata-4.9.dist-info/top_level.txt
pdfextractdata-4.9.dist-info/RECORD
