Metadata-Version: 2.1
Name: pdfextractdata
Version: 4.9
Summary: Python package for extracting data from pdf
Home-page: https://github.com/p829911/pdf-extract-data
Author: p829911
Author-email: p829911@gmail.com
License: UNKNOWN
Keywords: pdf extract,extract data from pdf,extract from pdf
Platform: UNKNOWN
Requires-Python: >=3
Requires-Dist: camelot-py[cv]
